pycce/__init__.py
pycce/center.py
pycce/constants.py
pycce/filter.py
pycce/find_clusters.py
pycce/main.py
pycce/sm.py
pycce/utilities.py
pycce/bath/__init__.py
pycce/bath/array.py
pycce/bath/cell.py
pycce/bath/cube.py
pycce/bath/isotopes.txt
pycce/bath/map.py
pycce/bath/state.py
pycce/h/__init__.py
pycce/h/base.py
pycce/h/functions.py
pycce/h/total.py
pycce/io/__init__.py
pycce/io/base.py
pycce/io/orca.py
pycce/io/qe.py
pycce/io/xyz.py
pycce/run/__init__.py
pycce/run/base.py
pycce/run/cce.py
pycce/run/clusters.py
pycce/run/corr.py
pycce/run/gcce.py
pycce/run/mastereq.py
pycce/run/mc.py
pycce/run/pulses.py
pycce/u/__init__.py
pycce/u/base.py
pycce-1.1.1.dist-info/LICENCE.md
pycce-1.1.1.dist-info/METADATA
pycce-1.1.1.dist-info/WHEEL
pycce-1.1.1.dist-info/top_level.txt
pycce-1.1.1.dist-info/RECORD
