Metadata-Version: 2.1
Name: pycce
Version: 1.1.1
Summary: A package to compute spin dynamics using CCE method
Home-page: 
Author: Nikita Onizhuk
Author-email: onizhuk@uchicago.edu
License-File: LICENCE.md
Requires-Dist: numpy
Requires-Dist: scipy
Requires-Dist: ase
Requires-Dist: pandas
Requires-Dist: numba
